pairiscope/__init__.py
pairiscope/bloom.py
pairiscope/input.py
pairiscope/pairiscope.py
pairiscope-0.0.3.dist-info/METADATA
pairiscope-0.0.3.dist-info/WHEEL
pairiscope-0.0.3.dist-info/licenses/LICENSE
pairiscope-0.0.3.dist-info/RECORD
