Metadata-Version: 2.1
Name: pairiscope
Version: 0.0.3
Summary: Pairiscope: A utility for exploring relations in microbial ecology count table data
Project-URL: Homepage, https://github.com/mwhall/pairiscope
Project-URL: Bug Tracker, https://github.com/mwhall/pairiscope/issues
Author-email: Mike Hall <mike.hall@dal.ca>
License-File: LICENSE
Classifier: License :: OSI Approved :: MIT License
Classifier: Operating System :: OS Independent
Classifier: Programming Language :: Python :: 3
Requires-Python: >=3.7
